ku_phone_num_validator/__init__.py
ku_phone_num_validator/validator.py
ku_phone_num_validator-0.1.1.dist-info/METADATA
ku_phone_num_validator-0.1.1.dist-info/WHEEL
ku_phone_num_validator-0.1.1.dist-info/RECORD
